{
"status": "success",
        "data": {
        "WorkOrders": [
        {
        "id": 1,
                "title": "first title loooooooooooooooooooooooooooong",
                "subtitle": "firstSubtitle looooooooooooooooooooooooooooooong",
                "statusId": 1,
                "Site": {
                "id": 1,
                        "title": "Site 1 title",
                        "description": "Shis super site is wery looooooooooooooooooooooooooooooooooooong",
                        "location": "London",
                        "lat": 51.508742,
                        "lng": - 0.065918,
                        "statusId": 1,
                        "Images": [
                        {
                        "url": "relative_path_to_image_without_host_name.jpg",
                                "someOherParamLikeNameOrOther": "some....",
                                "width": 500,
                                "height": 300
                        }, {
                        "url": "relative_path_to_image_without_host_name.jpg",
                                "other": "........."
                        }
                        ],
                        "Photos":[
                        {
                            "id": "17",
                            "name": "541b134e89d94_cbd794_full.jpg",
                            "path": "/root/ooh/541b134e89d94_cbd794_full.jpg",
                            "taskId": "40",
                            "url": "http://app.oohmanager.com/attachments/task/photos/40/541b134e89d94_cbd794_full.jpg",
                            "createdOn" : "2014-....",
                            "uid" : "weeweqw_ewewqe_fsdfdf_sdfsdf",
                            "type" :  "question or task"
                            "ownerId" : 137,  // contractor or admin id
                            "ownerName" : "Paul"  // contractor or admin username
                            "parentId" : -1, // task or answer id
                            "parentUid" : "weeweqw_ewewqe_fsdfdf_sdfsdf", // parent task or answer uid
                        }
                        ]
                        "Documents":[
                        {
                        "id": 1,
                                "name": "some name",
                                "url": "relative_path_to_document_without_host_name.pdf"
                        },
                        {
                        "id": 2,
                                "name": "another name",
                                "url": "relative_path_to_document_without_host_name.pdf"
                        }
                        ]
                },
                "Questions": [{
                "id": 1,
                        "cid": "c11",
                        "questionTypeId": 1,
                        "questionEnumId": 3,
                        "required": true,
                        "json": {
                        "label": "Question number 1",
                                "field_type": "checkboxes",
                                "required": true,
                                "field_options": {
                                "options": [{
                                "label": "label1",
                                        "checked": false
                                }, {
                                "label": "label2",
                                        "checked": false
                                }],
                                        "cid": "c11"
                                }
                        }
                }, {
                "id": 2,
                        "cid": "c16",
                        "questionTypeId": 1,
                        "questionEnumId": 7,
                        "required": true,
                        "json": {
                        "label": "Question number 2",
                                "field_type": "dropdown",
                                "required": true,
                                "field_options": {
                                "options": [{
                                "label": "option 1",
                                        "checked": false
                                }, {
                                "label": "option 2",
                                        "checked": false
                                }],
                                        "include_blank_option": false
                                },
                                "cid": "c16"
                        }
                }, {
                "id": 6,
                        "cid": "c8",
                        "questionTypeId": 1,
                        "questionEnumId": 2,
                        "required": false,
                        "json": {
                        "label": "Question with File",
                                "field_type": "file",
                                "required": true,
                                "field_options": {},
                                "cid": "c8"
                        }
                }, {
                "id": 3,
                        "cid": "c16",
                        "questionTypeId": 1,
                        "questionEnumId": 7,
                        "required": true,
                        "json": {
                        "label": "Question number 3",
                                "field_type": "dropdown",
                                "required": true,
                                "field_options": {
                                "options": [{
                                "label": " yes",
                                        "checked": false
                                }, {
                                "label": "no",
                                        "checked": false
                                }],
                                        "include_blank_option": false
                                },
                                "cid": "c16"
                        }
                }, {
                "id": 4,
                        "cid": "c24",
                        "questionTypeId": 1,
                        "questionEnumId": 1,
                        "required": true,
                        "json": {
                        "label": "Question number 4",
                                "field_type": "text",
                                "required": true,
                                "field_options": {
                                "size": "small"
                                },
                                "cid": "c24"
                        }
                }, {
                "id": 5,
                        "cid": "c16",
                        "questionTypeId": 1,
                        "questionEnumId": 8,
                        "required": false,
                        "json": {
                        "label": "Question #5 radio",
                                "field_type": "radio",
                                "required": true,
                                "field_options": {
                                "options": [{
                                "label": "radio 1",
                                        "checked": false
                                }, {
                                "label": "radio 2",
                                        "checked": false
                                }]
                                },
                                "cid": "c16"
                        }
                }],
                "Tasks": [{
                "id": 1,
                        "workOrderId": 1,
                        "title": "task title 1 loooooooooooooooooooooooooooong",
                        "subtitle": "task1 subtitle loooooooooooooooooooooooooooong",
                        "statusId": 1,
                        "time": "2014-12-25 10:59:00",
                        "description": " <span> [task1] </span> super <ul><li> li 1 </li> <li> li 1 </li></ul> long html content witn images and html tags,  sed do eiusmod tempor incididunt ut labore et dolore magna aliqua. Ut enim ad minim veniam, quis nostrud exercitation ullamco laboris  nisi ut aliquip ex ea commodo consequat. Duis aute irure dolor in reprehend erit in voluptate velit esse cillum dolore eu fugiat la pariatur. Excepteur sint occaecat cupidatat non proident, sunt in culpa qui officia deserunt mollit anim id est laborum",
                        "dateEnd": "25/12/2014",
                        "Comments": [{
                        "id": 1,
                                "taskId": 1,
                                "uid": "qwqwwe-qwqw-wqweww-weqeqweqwe",
                                "text": "comment for task 1"
                        }, {
                        "id": 2,
                                "taskId": 1,
                                "uid": "qwerty2",
                                "text": "comment for task 2"
                        }],
                        "Photos": [{
                        "id": 1,
                                "taskId": 1,
                                "uid": "qwerty-qwer-qwer-qwerty",
                                "name": "cool photo",
                                "url": "http://www.arhinovosti.ru/wp-content/uploads/2013/01/Office-Building-in-Liestal-1.jpg",
                                "path": "/root/ooh/img1.jpg  ====its local path for android device"
                        }, {
                        "id": 2,
                                "taskId": 1,
                                "uid": "zxxcv-zxxc-zxcc-zxcvb",
                                "name": "cool photo",
                                "url": "http://www.arhinovosti.ru/wp-content/uploads/2012/05/Centre-for-Life-Sciences-1.jpg",
                                "localPath": "/root/ooh/img2.jpg  ====its local path for android device "
                        }]

                }, {
                "id": 2,
                        "title": "task title 2",
                        "subtitle": "task2 subtitle",
                        "statusId": 4,
                        "time": "2014-08-25 15:59:00",
                        "description": " [task2] super long html content witn images and html tags ",
                        "dateEnd": "26/12/2014"
                }, {
                "id": 3,
                        "title": "task title 3",
                        "subtitle": "task3 subtitle",
                        "statusId": 5,
                        "time": "2014-08-25 12:48:00",
                        "description": "  <span> [task1] </span> super <ul><li> li 1 </li> <li> li 1 </li></ul> long html content witn images and html tags,  sed do eiusmod tempor incididunt ut labore et dolore magna aliqua. Ut enim ad minim veniam, quis nostrud exercitation ullamco laboris  nisi ut aliquip ex ea commodo consequat. Duis aute irure dolor in reprehend erit in voluptate velit esse cillum dolore eu fugiat la pariatur. Excepteur sint occaecat cupidatat non proident, sunt in culpa qui officia deserunt mollit anim id est laborum  <span> [task1] </span> super <ul><li> li 1 </li> <li> li 1 </li></ul> long html content witn images and html tags,  sed do eiusmod tempor incididunt ut labore et dolore magna aliqua. Ut enim ad minim veniam, quis nostrud exercitation ullamco laboris  nisi ut aliquip ex ea commodo consequat. Duis aute irure dolor in reprehend erit in voluptate velit esse cillum dolore eu fugiat la pariatur. Excepteur sint occaecat cupidatat non proident, sunt in culpa qui officia deserunt mollit anim id est laborum ",
                        "dateEnd": "27/12/2014"
                }, {
                "id": 4,
                        "title": "task title 4",
                        "subtitle": "task3 subtitle",
                        "statusId": 5,
                        "time": "2014-08-25 15:59:00",
                        "description": "  <span> [task1] </span> super <ul><li> li 1 </li> <li> li 1 </li></ul> long html content witn images and html tags,  sed do eiusmod tempor incididunt ut labore et dolore magna aliqua. Ut enim ad minim veniam, quis nostrud exercitation ullamco laboris  nisi ut aliquip ex ea commodo consequat. Duis aute irure dolor in reprehend erit in voluptate velit esse cillum dolore eu fugiat la pariatur. Excepteur sint occaecat cupidatat non proident, sunt in culpa qui officia deserunt mollit anim id est laborum  <span> [task1] </span> super <ul><li> li 1 </li> <li> li 1 </li></ul> long html content witn images and html tags,  sed do eiusmod tempor incididunt ut labore et dolore magna aliqua. Ut enim ad minim veniam, quis nostrud exercitation ullamco laboris  nisi ut aliquip ex ea commodo consequat. Duis aute irure dolor in reprehend erit in voluptate velit esse cillum dolore eu fugiat la pariatur. Excepteur sint occaecat cupidatat non proident, sunt in culpa qui officia deserunt mollit anim id est laborum ",
                        "dateEnd": "27/12/2014"
                }, {
                "id": 5,
                        "title": "task title 5",
                        "subtitle": "task3 subtitle",
                        "statusId": 5,
                        "time": "2014-08-25 15:59:00",
                        "description": "  <span> [task1] </span> super <ul><li> li 1 </li> <li> li 1 </li></ul> long html content witn images and html tags,  sed do eiusmod tempor incididunt ut labore et dolore magna aliqua. Ut enim ad minim veniam, quis nostrud exercitation ullamco laboris  nisi ut aliquip ex ea commodo consequat. Duis aute irure dolor in reprehend erit in voluptate velit esse cillum dolore eu fugiat la pariatur. Excepteur sint occaecat cupidatat non proident, sunt in culpa qui officia deserunt mollit anim id est laborum  <span> [task1] </span> super <ul><li> li 1 </li> <li> li 1 </li></ul> long html content witn images and html tags,  sed do eiusmod tempor incididunt ut labore et dolore magna aliqua. Ut enim ad minim veniam, quis nostrud exercitation ullamco laboris  nisi ut aliquip ex ea commodo consequat. Duis aute irure dolor in reprehend erit in voluptate velit esse cillum dolore eu fugiat la pariatur. Excepteur sint occaecat cupidatat non proident, sunt in culpa qui officia deserunt mollit anim id est laborum ",
                        "dateEnd": "27/12/2014"
                }, {
                "id": 6,
                        "title": "task title 6",
                        "subtitle": "task3 subtitle",
                        "statusId": 4,
                        "time": "2014-08-25 15:59:00",
                        "description": "  <span> [task1] </span> super <ul><li> li 1 </li> <li> li 1 </li></ul> long html content witn images and html tags,  sed do eiusmod tempor incididunt ut labore et dolore magna aliqua. Ut enim ad minim veniam, quis nostrud exercitation ullamco laboris  nisi ut aliquip ex ea commodo consequat. Duis aute irure dolor in reprehend erit in voluptate velit esse cillum dolore eu fugiat la pariatur. Excepteur sint occaecat cupidatat non proident, sunt in culpa qui officia deserunt mollit anim id est laborum  <span> [task1] </span> super <ul><li> li 1 </li> <li> li 1 </li></ul> long html content witn images and html tags,  sed do eiusmod tempor incididunt ut labore et dolore magna aliqua. Ut enim ad minim veniam, quis nostrud exercitation ullamco laboris  nisi ut aliquip ex ea commodo consequat. Duis aute irure dolor in reprehend erit in voluptate velit esse cillum dolore eu fugiat la pariatur. Excepteur sint occaecat cupidatat non proident, sunt in culpa qui officia deserunt mollit anim id est laborum ",
                        "dateEnd": "27/12/2014"
                }, {
                "id": 7,
                        "title": "task title 7",
                        "subtitle": "task3 subtitle",
                        "statusId": 1,
                        "time": "2014-08-25 15:59:00",
                        "description": "  <span> [task1] </span> super <ul><li> li 1 </li> <li> li 1 </li></ul> long html content witn images and html tags,  sed do eiusmod tempor incididunt ut labore et dolore magna aliqua. Ut enim ad minim veniam, quis nostrud exercitation ullamco laboris  nisi ut aliquip ex ea commodo consequat. Duis aute irure dolor in reprehend erit in voluptate velit esse cillum dolore eu fugiat la pariatur. Excepteur sint occaecat cupidatat non proident, sunt in culpa qui officia deserunt mollit anim id est laborum  <span> [task1] </span> super <ul><li> li 1 </li> <li> li 1 </li></ul> long html content witn images and html tags,  sed do eiusmod tempor incididunt ut labore et dolore magna aliqua. Ut enim ad minim veniam, quis nostrud exercitation ullamco laboris  nisi ut aliquip ex ea commodo consequat. Duis aute irure dolor in reprehend erit in voluptate velit esse cillum dolore eu fugiat la pariatur. Excepteur sint occaecat cupidatat non proident, sunt in culpa qui officia deserunt mollit anim id est laborum ",
                        "dateEnd": "27/12/2014"
                }, {
                "id": 8,
                        "title": "task title 8",
                        "subtitle": "task3 subtitle",
                        "statusId": 1,
                        "time": "2014-08-25 15:59:00",
                        "description": "  <span> [task1] </span> super <ul><li> li 1 </li> <li> li 1 </li></ul> long html content witn images and html tags,  sed do eiusmod tempor incididunt ut labore et dolore magna aliqua. Ut enim ad minim veniam, quis nostrud exercitation ullamco laboris  nisi ut aliquip ex ea commodo consequat. Duis aute irure dolor in reprehend erit in voluptate velit esse cillum dolore eu fugiat la pariatur. Excepteur sint occaecat cupidatat non proident, sunt in culpa qui officia deserunt mollit anim id est laborum  <span> [task1] </span> super <ul><li> li 1 </li> <li> li 1 </li></ul> long html content witn images and html tags,  sed do eiusmod tempor incididunt ut labore et dolore magna aliqua. Ut enim ad minim veniam, quis nostrud exercitation ullamco laboris  nisi ut aliquip ex ea commodo consequat. Duis aute irure dolor in reprehend erit in voluptate velit esse cillum dolore eu fugiat la pariatur. Excepteur sint occaecat cupidatat non proident, sunt in culpa qui officia deserunt mollit anim id est laborum ",
                        "dateEnd": "27/12/2014"
                }, {
                "id": 9,
                        "title": "task title 9",
                        "subtitle": "task3 subtitle",
                        "statusId": 2,
                        "time": "2014-08-25 15:59:00",
                        "description": "  <span> [task1] </span> super <ul><li> li 1 </li> <li> li 1 </li></ul> long html content witn images and html tags,  sed do eiusmod tempor incididunt ut labore et dolore magna aliqua. Ut enim ad minim veniam, quis nostrud exercitation ullamco laboris  nisi ut aliquip ex ea commodo consequat. Duis aute irure dolor in reprehend erit in voluptate velit esse cillum dolore eu fugiat la pariatur. Excepteur sint occaecat cupidatat non proident, sunt in culpa qui officia deserunt mollit anim id est laborum  <span> [task1] </span> super <ul><li> li 1 </li> <li> li 1 </li></ul> long html content witn images and html tags,  sed do eiusmod tempor incididunt ut labore et dolore magna aliqua. Ut enim ad minim veniam, quis nostrud exercitation ullamco laboris  nisi ut aliquip ex ea commodo consequat. Duis aute irure dolor in reprehend erit in voluptate velit esse cillum dolore eu fugiat la pariatur. Excepteur sint occaecat cupidatat non proident, sunt in culpa qui officia deserunt mollit anim id est laborum ",
                        "dateEnd": "27/12/2014"
                }, {
                "id": 10,
                        "title": "task title 10",
                        "subtitle": "task3 subtitle",
                        "statusId": 3,
                        "time": "2014-08-25 15:59:00",
                        "description": "  <span> [task1] </span> super <ul><li> li 1 </li> <li> li 1 </li></ul> long html content witn images and html tags,  sed do eiusmod tempor incididunt ut labore et dolore magna aliqua. Ut enim ad minim veniam, quis nostrud exercitation ullamco laboris  nisi ut aliquip ex ea commodo consequat. Duis aute irure dolor in reprehend erit in voluptate velit esse cillum dolore eu fugiat la pariatur. Excepteur sint occaecat cupidatat non proident, sunt in culpa qui officia deserunt mollit anim id est laborum  <span> [task1] </span> super <ul><li> li 1 </li> <li> li 1 </li></ul> long html content witn images and html tags,  sed do eiusmod tempor incididunt ut labore et dolore magna aliqua. Ut enim ad minim veniam, quis nostrud exercitation ullamco laboris  nisi ut aliquip ex ea commodo consequat. Duis aute irure dolor in reprehend erit in voluptate velit esse cillum dolore eu fugiat la pariatur. Excepteur sint occaecat cupidatat non proident, sunt in culpa qui officia deserunt mollit anim id est laborum ",
                        "dateEnd": "27/12/2014"
                }, {
                "id": 11,
                        "title": "task title 11",
                        "subtitle": "task3 subtitle",
                        "statusId": 4,
                        "time": "2014-08-25 15:59:00",
                        "description": "  <span> [task1] </span> super <ul><li> li 1 </li> <li> li 1 </li></ul> long html content witn images and html tags,  sed do eiusmod tempor incididunt ut labore et dolore magna aliqua. Ut enim ad minim veniam, quis nostrud exercitation ullamco laboris  nisi ut aliquip ex ea commodo consequat. Duis aute irure dolor in reprehend erit in voluptate velit esse cillum dolore eu fugiat la pariatur. Excepteur sint occaecat cupidatat non proident, sunt in culpa qui officia deserunt mollit anim id est laborum  <span> [task1] </span> super <ul><li> li 1 </li> <li> li 1 </li></ul> long html content witn images and html tags,  sed do eiusmod tempor incididunt ut labore et dolore magna aliqua. Ut enim ad minim veniam, quis nostrud exercitation ullamco laboris  nisi ut aliquip ex ea commodo consequat. Duis aute irure dolor in reprehend erit in voluptate velit esse cillum dolore eu fugiat la pariatur. Excepteur sint occaecat cupidatat non proident, sunt in culpa qui officia deserunt mollit anim id est laborum ",
                        "dateEnd": "27/12/2014"
                }

                ]
        }, {
        "id": 2,
                "title": "second title",
                "subtitle": "Second Subtitle",
                "statusId": 1,
                "Tasks": [{
                "id": 12,
                        "workOrderId": 2,
                        "title": "task title 11",
                        "subtitle": "task1 description",
                        "statusId": 5,
                        "time": "2014-08-25 15:59:00",
                        "description": " [task1] super long html content witn images and html tags ",
                        "dateEnd": "25/12/2014"
                }, {
                "id": 13,
                        "title": "task title 12",
                        "subtitle": "task2 description",
                        "statusId": 5,
                        "time": "2014-08-25 15:59:00",
                        "description": " [task2] super long html content witn images and html tags ",
                        "dateEnd": "26/12/2014"
                }, {
                "id": 14,
                        "title": "task title 13",
                        "subtitle": "task3 description",
                        "statusId": 5,
                        "time": "2014-08-25 15:59:00",
                        "description": " [task3] super long html content witn images and html tags ",
                        "dateEnd": "27/12/2014"
                }
                ],
                "Questions": [{
                "id": 1,
                        "cid": "c11",
                        "questionTypeId": 1,
                        "questionEnumId": 3,
                        "required": true,
                        "json": {
                        "label": "Question number 1",
                                "field_type": "checkboxes",
                                "required": true,
                                "field_options": {
                                "options": [{
                                "label": "label1",
                                        "checked": false
                                }, {
                                "label": "label2",
                                        "checked": false
                                }],
                                        "cid": "c11"
                                }
                        }
                }, {
                "id": 2,
                        "cid": "c16",
                        "questionTypeId": 1,
                        "questionEnumId": 7,
                        "required": true,
                        "json": {
                        "label": "Question number 2",
                                "field_type": "dropdown",
                                "required": true,
                                "field_options": {
                                "options": [{
                                "label": "option 1",
                                        "checked": false
                                }, {
                                "label": "option 2",
                                        "checked": false
                                }],
                                        "include_blank_option": false
                                },
                                "cid": "c16"
                        }
                }, {
                "id": 6,
                        "cid": "c8",
                        "questionTypeId": 1,
                        "questionEnumId": 2,
                        "required": false,
                        "json": {
                        "label": "Question with File",
                                "field_type": "file",
                                "required": true,
                                "field_options": {},
                                "cid": "c8"
                        }
                }, {
                "id": 3,
                        "cid": "c16",
                        "questionTypeId": 1,
                        "questionEnumId": 7,
                        "required": true,
                        "json": {
                        "label": "Question number 3",
                                "field_type": "dropdown",
                                "required": true,
                                "field_options": {
                                "options": [{
                                "label": " yes",
                                        "checked": false
                                }, {
                                "label": "no",
                                        "checked": false
                                }],
                                        "include_blank_option": false
                                },
                                "cid": "c16"
                        }
                }, {
                "id": 4,
                        "cid": "c24",
                        "questionTypeId": 1,
                        "questionEnumId": 1,
                        "required": true,
                        "json": {
                        "label": "Question number 4",
                                "field_type": "text",
                                "required": true,
                                "field_options": {
                                "size": "small"
                                },
                                "cid": "c24"
                        }
                }, {
                "id": 5,
                        "cid": "c16",
                        "questionTypeId": 1,
                        "questionEnumId": 8,
                        "required": false,
                        "json": {
                        "label": "Question #5 radio",
                                "field_type": "radio",
                                "required": true,
                                "field_options": {
                                "options": [{
                                "label": "radio 1",
                                        "checked": false
                                }, {
                                "label": "radio 2",
                                        "checked": false
                                }]
                                },
                                "cid": "c16"
                        }
                }]

        }, {
        "id": 3,
                "title": "first title loooooooooooooooooooooooooooong",
                "subtitle": "firstSubtitle looooooooooooooooooooooooooooooong",
                "Tasks": [{
                "id": 1,
                        "workOrderId": 3,
                        "title": "task title 1 loooooooooooooooooooooooooooong",
                        "subtitle": "task1 subtitle loooooooooooooooooooooooooooong",
                        "statusId": 5,
                        "time": "2014-08-25 15:59:00",
                        "description": " <span> [task1] </span> super <ul><li> li 1 </li> <li> li 1 </li></ul> long html content witn images and html tags,  sed do eiusmod tempor incididunt ut labore et dolore magna aliqua. Ut enim ad minim veniam, quis nostrud exercitation ullamco laboris  nisi ut aliquip ex ea commodo consequat. Duis aute irure dolor in reprehend erit in voluptate velit esse cillum dolore eu fugiat la pariatur. Excepteur sint occaecat cupidatat non proident, sunt in culpa qui officia deserunt mollit anim id est laborum",
                        "dateEnd": "25/12/2014"
                }, {
                "id": 2,
                        "title": "task title 2",
                        "subtitle": "task2 subtitle",
                        "statusId": 4,
                        "time": "2014-08-25 15:59:00",
                        "description": " [task2] super long html content witn images and html tags ",
                        "dateEnd": "26/12/2014"
                }, {
                "id": 3,
                        "title": "task title 3",
                        "subtitle": "task3 subtitle",
                        "statusId": 4,
                        "time": "2014-08-25 15:59:00",
                        "description": "  <span> [task1] </span> super <ul><li> li 1 </li> <li> li 1 </li></ul> long html content witn images and html tags,  sed do eiusmod tempor incididunt ut labore et dolore magna aliqua. Ut enim ad minim veniam, quis nostrud exercitation ullamco laboris  nisi ut aliquip ex ea commodo consequat. Duis aute irure dolor in reprehend erit in voluptate velit esse cillum dolore eu fugiat la pariatur. Excepteur sint occaecat cupidatat non proident, sunt in culpa qui officia deserunt mollit anim id est laborum  <span> [task1] </span> super <ul><li> li 1 </li> <li> li 1 </li></ul> long html content witn images and html tags,  sed do eiusmod tempor incididunt ut labore et dolore magna aliqua. Ut enim ad minim veniam, quis nostrud exercitation ullamco laboris  nisi ut aliquip ex ea commodo consequat. Duis aute irure dolor in reprehend erit in voluptate velit esse cillum dolore eu fugiat la pariatur. Excepteur sint occaecat cupidatat non proident, sunt in culpa qui officia deserunt mollit anim id est laborum ",
                        "dateEnd": "27/12/2014"
                }
                ]
        }, {
        "id": 4,
                "title": "first title loooooooooooooooooooooooooooong",
                "subtitle": "firstSubtitle looooooooooooooooooooooooooooooong",
                "Tasks": [{
                "id": 1,
                        "title": "task title 1 loooooooooooooooooooooooooooong",
                        "subtitle": "task1 subtitle loooooooooooooooooooooooooooong",
                        "statusId": 5,
                        "time": "2014-08-25 15:59:00",
                        "description": " <span> [task1] </span> super <ul><li> li 1 </li> <li> li 1 </li></ul> long html content witn images and html tags,  sed do eiusmod tempor incididunt ut labore et dolore magna aliqua. Ut enim ad minim veniam, quis nostrud exercitation ullamco laboris  nisi ut aliquip ex ea commodo consequat. Duis aute irure dolor in reprehend erit in voluptate velit esse cillum dolore eu fugiat la pariatur. Excepteur sint occaecat cupidatat non proident, sunt in culpa qui officia deserunt mollit anim id est laborum",
                        "dateEnd": "25/12/2014"
                }, {
                "id": 2,
                        "title": "task title 2",
                        "subtitle": "task2 subtitle",
                        "statusId": 4,
                        "time": "2014-08-25 15:59:00",
                        "description": " [task2] super long html content witn images and html tags ",
                        "dateEnd": "26/12/2014"
                }, {
                "id": 3,
                        "title": "task title 3",
                        "subtitle": "task3 subtitle",
                        "statusId": 1,
                        "time": "2014-08-25 15:59:00",
                        "description": "  <span> [task1] </span> super <ul><li> li 1 </li> <li> li 1 </li></ul> long html content witn images and html tags,  sed do eiusmod tempor incididunt ut labore et dolore magna aliqua. Ut enim ad minim veniam, quis nostrud exercitation ullamco laboris  nisi ut aliquip ex ea commodo consequat. Duis aute irure dolor in reprehend erit in voluptate velit esse cillum dolore eu fugiat la pariatur. Excepteur sint occaecat cupidatat non proident, sunt in culpa qui officia deserunt mollit anim id est laborum  <span> [task1] </span> super <ul><li> li 1 </li> <li> li 1 </li></ul> long html content witn images and html tags,  sed do eiusmod tempor incididunt ut labore et dolore magna aliqua. Ut enim ad minim veniam, quis nostrud exercitation ullamco laboris  nisi ut aliquip ex ea commodo consequat. Duis aute irure dolor in reprehend erit in voluptate velit esse cillum dolore eu fugiat la pariatur. Excepteur sint occaecat cupidatat non proident, sunt in culpa qui officia deserunt mollit anim id est laborum ",
                        "dateEnd": "27/12/2014"
                }
                ]
        }, {
        "id": 5,
                "title": "first title loooooooooooooooooooooooooooong",
                "subtitle": "firstSubtitle looooooooooooooooooooooooooooooong",
                "Tasks": [{
                "id": 1,
                        "title": "task title 1 loooooooooooooooooooooooooooong",
                        "subtitle": "task1 subtitle loooooooooooooooooooooooooooong",
                        "statusId": 4,
                        "time": "2014-08-25 15:59:00",
                        "description": " <span> [task1] </span> super <ul><li> li 1 </li> <li> li 1 </li></ul> long html content witn images and html tags,  sed do eiusmod tempor incididunt ut labore et dolore magna aliqua. Ut enim ad minim veniam, quis nostrud exercitation ullamco laboris  nisi ut aliquip ex ea commodo consequat. Duis aute irure dolor in reprehend erit in voluptate velit esse cillum dolore eu fugiat la pariatur. Excepteur sint occaecat cupidatat non proident, sunt in culpa qui officia deserunt mollit anim id est laborum",
                        "dateEnd": "25/12/2014"
                }, {
                "id": 2,
                        "title": "task title 2",
                        "subtitle": "task2 subtitle",
                        "statusId": 5,
                        "time": "2014-08-25 15:59:00",
                        "description": " [task2] super long html content witn images and html tags ",
                        "dateEnd": "26/12/2014"
                }, {
                "id": 3,
                        "title": "task title 3",
                        "subtitle": "task3 subtitle",
                        "statusId": 1,
                        "time": "2014-08-25 15:59:00",
                        "description": "  <span> [task1] </span> super <ul><li> li 1 </li> <li> li 1 </li></ul> long html content witn images and html tags,  sed do eiusmod tempor incididunt ut labore et dolore magna aliqua. Ut enim ad minim veniam, quis nostrud exercitation ullamco laboris  nisi ut aliquip ex ea commodo consequat. Duis aute irure dolor in reprehend erit in voluptate velit esse cillum dolore eu fugiat la pariatur. Excepteur sint occaecat cupidatat non proident, sunt in culpa qui officia deserunt mollit anim id est laborum  <span> [task1] </span> super <ul><li> li 1 </li> <li> li 1 </li></ul> long html content witn images and html tags,  sed do eiusmod tempor incididunt ut labore et dolore magna aliqua. Ut enim ad minim veniam, quis nostrud exercitation ullamco laboris  nisi ut aliquip ex ea commodo consequat. Duis aute irure dolor in reprehend erit in voluptate velit esse cillum dolore eu fugiat la pariatur. Excepteur sint occaecat cupidatat non proident, sunt in culpa qui officia deserunt mollit anim id est laborum ",
                        "dateEnd": "27/12/2014"
                }
                ]
        }, {
        "id": 6,
                "title": "first title loooooooooooooooooooooooooooong",
                "subtitle": "firstSubtitle looooooooooooooooooooooooooooooong",
                "Tasks": [{
                "id": 1,
                        "title": "task title 1 loooooooooooooooooooooooooooong",
                        "subtitle": "task1 subtitle loooooooooooooooooooooooooooong",
                        "statusId": 2,
                        "time": "2014-08-25 15:59:00",
                        "description": " <span> [task1] </span> super <ul><li> li 1 </li> <li> li 1 </li></ul> long html content witn images and html tags,  sed do eiusmod tempor incididunt ut labore et dolore magna aliqua. Ut enim ad minim veniam, quis nostrud exercitation ullamco laboris  nisi ut aliquip ex ea commodo consequat. Duis aute irure dolor in reprehend erit in voluptate velit esse cillum dolore eu fugiat la pariatur. Excepteur sint occaecat cupidatat non proident, sunt in culpa qui officia deserunt mollit anim id est laborum",
                        "dateEnd": "25/12/2014"
                }, {
                "id": 2,
                        "title": "task title 2",
                        "subtitle": "task2 subtitle",
                        "statusId": 3,
                        "time": "2014-08-25 15:59:00",
                        "description": " [task2] super long html content witn images and html tags ",
                        "dateEnd": "26/12/2014"
                }, {
                "id": 3,
                        "title": "task title 3",
                        "subtitle": "task3 subtitle",
                        "statusId": 4,
                        "time": "2014-08-25 15:59:00",
                        "description": "  <span> [task1] </span> super <ul><li> li 1 </li> <li> li 1 </li></ul> long html content witn images and html tags,  sed do eiusmod tempor incididunt ut labore et dolore magna aliqua. Ut enim ad minim veniam, quis nostrud exercitation ullamco laboris  nisi ut aliquip ex ea commodo consequat. Duis aute irure dolor in reprehend erit in voluptate velit esse cillum dolore eu fugiat la pariatur. Excepteur sint occaecat cupidatat non proident, sunt in culpa qui officia deserunt mollit anim id est laborum  <span> [task1] </span> super <ul><li> li 1 </li> <li> li 1 </li></ul> long html content witn images and html tags,  sed do eiusmod tempor incididunt ut labore et dolore magna aliqua. Ut enim ad minim veniam, quis nostrud exercitation ullamco laboris  nisi ut aliquip ex ea commodo consequat. Duis aute irure dolor in reprehend erit in voluptate velit esse cillum dolore eu fugiat la pariatur. Excepteur sint occaecat cupidatat non proident, sunt in culpa qui officia deserunt mollit anim id est laborum ",
                        "dateEnd": "27/12/2014"
                }
                ]
        }, {
        "id": 7,
                "title": "first title loooooooooooooooooooooooooooong",
                "subtitle": "firstSubtitle looooooooooooooooooooooooooooooong",
                "Tasks": [{
                "id": 1,
                        "title": "task title 1 loooooooooooooooooooooooooooong",
                        "subtitle": "task1 subtitle loooooooooooooooooooooooooooong",
                        "statusId": 1,
                        "time": "2014-08-25 15:59:00",
                        "description": " <span> [task1] </span> super <ul><li> li 1 </li> <li> li 1 </li></ul> long html content witn images and html tags,  sed do eiusmod tempor incididunt ut labore et dolore magna aliqua. Ut enim ad minim veniam, quis nostrud exercitation ullamco laboris  nisi ut aliquip ex ea commodo consequat. Duis aute irure dolor in reprehend erit in voluptate velit esse cillum dolore eu fugiat la pariatur. Excepteur sint occaecat cupidatat non proident, sunt in culpa qui officia deserunt mollit anim id est laborum",
                        "dateEnd": "25/12/2014"
                }, {
                "id": 2,
                        "title": "task title 2",
                        "subtitle": "task2 subtitle",
                        "statusId": 2,
                        "description": " [task2] super long html content witn images and html tags ",
                        "dateEnd": "26/12/2014"
                }, {
                "id": 3,
                        "title": "task title 3",
                        "subtitle": "task3 subtitle",
                        "statusId": 3,
                        "time": "2014-08-25 15:59:00",
                        "description": "  <span> [task1] </span> super <ul><li> li 1 </li> <li> li 1 </li></ul> long html content witn images and html tags,  sed do eiusmod tempor incididunt ut labore et dolore magna aliqua. Ut enim ad minim veniam, quis nostrud exercitation ullamco laboris  nisi ut aliquip ex ea commodo consequat. Duis aute irure dolor in reprehend erit in voluptate velit esse cillum dolore eu fugiat la pariatur. Excepteur sint occaecat cupidatat non proident, sunt in culpa qui officia deserunt mollit anim id est laborum  <span> [task1] </span> super <ul><li> li 1 </li> <li> li 1 </li></ul> long html content witn images and html tags,  sed do eiusmod tempor incididunt ut labore et dolore magna aliqua. Ut enim ad minim veniam, quis nostrud exercitation ullamco laboris  nisi ut aliquip ex ea commodo consequat. Duis aute irure dolor in reprehend erit in voluptate velit esse cillum dolore eu fugiat la pariatur. Excepteur sint occaecat cupidatat non proident, sunt in culpa qui officia deserunt mollit anim id est laborum ",
                        "dateEnd": "27/12/2014"
                }
                ]
        }, {
        "id": 8,
                "title": "first title loooooooooooooooooooooooooooong",
                "subtitle": "firstSubtitle looooooooooooooooooooooooooooooong",
                "Tasks": [{
                "id": 1,
                        "title": "task title 1 loooooooooooooooooooooooooooong",
                        "subtitle": "task1 subtitle loooooooooooooooooooooooooooong",
                        "statusId": 4,
                        "time": "2014-08-25 15:59:00",
                        "description": " <span> [task1] </span> super <ul><li> li 1 </li> <li> li 1 </li></ul> long html content witn images and html tags,  sed do eiusmod tempor incididunt ut labore et dolore magna aliqua. Ut enim ad minim veniam, quis nostrud exercitation ullamco laboris  nisi ut aliquip ex ea commodo consequat. Duis aute irure dolor in reprehend erit in voluptate velit esse cillum dolore eu fugiat la pariatur. Excepteur sint occaecat cupidatat non proident, sunt in culpa qui officia deserunt mollit anim id est laborum",
                        "dateEnd": "25/12/2014"
                }, {
                "id": 2,
                        "title": "task title 2",
                        "subtitle": "task2 subtitle",
                        "statusId": 5,
                        "time": "2014-08-25 15:59:00",
                        "description": " [task2] super long html content witn images and html tags ",
                        "dateEnd": "26/12/2014"
                }, {
                "id": 3,
                        "title": "task title 3",
                        "subtitle": "task3 subtitle",
                        "statusId": 1,
                        "time": "2014-08-25 15:59:00",
                        "description": "  <span> [task1] </span> super <ul><li> li 1 </li> <li> li 1 </li></ul> long html content witn images and html tags,  sed do eiusmod tempor incididunt ut labore et dolore magna aliqua. Ut enim ad minim veniam, quis nostrud exercitation ullamco laboris  nisi ut aliquip ex ea commodo consequat. Duis aute irure dolor in reprehend erit in voluptate velit esse cillum dolore eu fugiat la pariatur. Excepteur sint occaecat cupidatat non proident, sunt in culpa qui officia deserunt mollit anim id est laborum  <span> [task1] </span> super <ul><li> li 1 </li> <li> li 1 </li></ul> long html content witn images and html tags,  sed do eiusmod tempor incididunt ut labore et dolore magna aliqua. Ut enim ad minim veniam, quis nostrud exercitation ullamco laboris  nisi ut aliquip ex ea commodo consequat. Duis aute irure dolor in reprehend erit in voluptate velit esse cillum dolore eu fugiat la pariatur. Excepteur sint occaecat cupidatat non proident, sunt in culpa qui officia deserunt mollit anim id est laborum ",
                        "dateEnd": "27/12/2014"
                }
                ]
        }, {
        "id": 9,
                "title": "first title loooooooooooooooooooooooooooong",
                "subtitle": "firstSubtitle looooooooooooooooooooooooooooooong",
                "Tasks": [{
                "id": 1,
                        "title": "task title 1 loooooooooooooooooooooooooooong",
                        "subtitle": "task1 subtitle loooooooooooooooooooooooooooong",
                        "statusId": 2,
                        "time": "2014-08-25 15:59:00",
                        "description": " <span> [task1] </span> super <ul><li> li 1 </li> <li> li 1 </li></ul> long html content witn images and html tags,  sed do eiusmod tempor incididunt ut labore et dolore magna aliqua. Ut enim ad minim veniam, quis nostrud exercitation ullamco laboris  nisi ut aliquip ex ea commodo consequat. Duis aute irure dolor in reprehend erit in voluptate velit esse cillum dolore eu fugiat la pariatur. Excepteur sint occaecat cupidatat non proident, sunt in culpa qui officia deserunt mollit anim id est laborum",
                        "dateEnd": "25/12/2014"
                }, {
                "id": 2,
                        "title": "task title 2",
                        "subtitle": "task2 subtitle",
                        "statusId": 3,
                        "time": "2014-08-25 15:59:00",
                        "description": " [task2] super long html content witn images and html tags ",
                        "dateEnd": "26/12/2014"
                }, {
                "id": 3,
                        "title": "task title 3",
                        "subtitle": "task3 subtitle",
                        "statusId": 4,
                        "time": "2014-08-25 15:59:00",
                        "description": "  <span> [task1] </span> super <ul><li> li 1 </li> <li> li 1 </li></ul> long html content witn images and html tags,  sed do eiusmod tempor incididunt ut labore et dolore magna aliqua. Ut enim ad minim veniam, quis nostrud exercitation ullamco laboris  nisi ut aliquip ex ea commodo consequat. Duis aute irure dolor in reprehend erit in voluptate velit esse cillum dolore eu fugiat la pariatur. Excepteur sint occaecat cupidatat non proident, sunt in culpa qui officia deserunt mollit anim id est laborum  <span> [task1] </span> super <ul><li> li 1 </li> <li> li 1 </li></ul> long html content witn images and html tags,  sed do eiusmod tempor incididunt ut labore et dolore magna aliqua. Ut enim ad minim veniam, quis nostrud exercitation ullamco laboris  nisi ut aliquip ex ea commodo consequat. Duis aute irure dolor in reprehend erit in voluptate velit esse cillum dolore eu fugiat la pariatur. Excepteur sint occaecat cupidatat non proident, sunt in culpa qui officia deserunt mollit anim id est laborum ",
                        "dateEnd": "27/12/2014"
                }
                ]
        }, {
        "id": 10,
                "title": "first title loooooooooooooooooooooooooooong",
                "subtitle": "firstSubtitle looooooooooooooooooooooooooooooong",
                "Tasks": [{
                "id": 1,
                        "title": "task title 1 loooooooooooooooooooooooooooong",
                        "subtitle": "task1 subtitle loooooooooooooooooooooooooooong",
                        "statusId": 5,
                        "time": "2014-08-25 15:59:00",
                        "description": " <span> [task1] </span> super <ul><li> li 1 </li> <li> li 1 </li></ul> long html content witn images and html tags,  sed do eiusmod tempor incididunt ut labore et dolore magna aliqua. Ut enim ad minim veniam, quis nostrud exercitation ullamco laboris  nisi ut aliquip ex ea commodo consequat. Duis aute irure dolor in reprehend erit in voluptate velit esse cillum dolore eu fugiat la pariatur. Excepteur sint occaecat cupidatat non proident, sunt in culpa qui officia deserunt mollit anim id est laborum",
                        "dateEnd": "25/12/2014"
                }, {
                "id": 2,
                        "title": "task title 2",
                        "subtitle": "task2 subtitle",
                        "statusId": 1,
                        "time": "2014-08-25 15:59:00",
                        "description": " [task2] super long html content witn images and html tags ",
                        "dateEnd": "26/12/2014"
                }, {
                "id": 3,
                        "title": "task title 3",
                        "subtitle": "task3 subtitle",
                        "statusId": 2,
                        "time": "2014-08-25 15:59:00",
                        "description": "  <span> [task1] </span> super <ul><li> li 1 </li> <li> li 1 </li></ul> long html content witn images and html tags,  sed do eiusmod tempor incididunt ut labore et dolore magna aliqua. Ut enim ad minim veniam, quis nostrud exercitation ullamco laboris  nisi ut aliquip ex ea commodo consequat. Duis aute irure dolor in reprehend erit in voluptate velit esse cillum dolore eu fugiat la pariatur. Excepteur sint occaecat cupidatat non proident, sunt in culpa qui officia deserunt mollit anim id est laborum  <span> [task1] </span> super <ul><li> li 1 </li> <li> li 1 </li></ul> long html content witn images and html tags,  sed do eiusmod tempor incididunt ut labore et dolore magna aliqua. Ut enim ad minim veniam, quis nostrud exercitation ullamco laboris  nisi ut aliquip ex ea commodo consequat. Duis aute irure dolor in reprehend erit in voluptate velit esse cillum dolore eu fugiat la pariatur. Excepteur sint occaecat cupidatat non proident, sunt in culpa qui officia deserunt mollit anim id est laborum ",
                        "dateEnd": "27/12/2014"
                }
                ]
        }, {
        "id": 11,
                "title": "first title loooooooooooooooooooooooooooong",
                "subtitle": "firstSubtitle looooooooooooooooooooooooooooooong",
                "statusId": 1,
                "Tasks": [{
                "id": 1,
                        "title": "task title 1 loooooooooooooooooooooooooooong",
                        "subtitle": "task1 subtitle loooooooooooooooooooooooooooong",
                        "statusId": 3,
                        "time": "2014-08-25 15:59:00",
                        "description": " <span> [task1] </span> super <ul><li> li 1 </li> <li> li 1 </li></ul> long html content witn images and html tags,  sed do eiusmod tempor incididunt ut labore et dolore magna aliqua. Ut enim ad minim veniam, quis nostrud exercitation ullamco laboris  nisi ut aliquip ex ea commodo consequat. Duis aute irure dolor in reprehend erit in voluptate velit esse cillum dolore eu fugiat la pariatur. Excepteur sint occaecat cupidatat non proident, sunt in culpa qui officia deserunt mollit anim id est laborum",
                        "dateEnd": "25/12/2014"
                }, {
                "id": 2,
                        "title": "task title 2",
                        "subtitle": "task2 subtitle",
                        "statusId": 4,
                        "time": "2014-08-25 15:59:00",
                        "description": " [task2] super long html content witn images and html tags ",
                        "dateEnd": "26/12/2014"
                }, {
                "id": 3,
                        "title": "task title 3",
                        "subtitle": "task3 subtitle",
                        "statusId": 5,
                        "time": "2014-08-25 15:59:00",
                        "description": "  <span> [task1] </span> super <ul><li> li 1 </li> <li> li 1 </li></ul> long html content witn images and html tags,  sed do eiusmod tempor incididunt ut labore et dolore magna aliqua. Ut enim ad minim veniam, quis nostrud exercitation ullamco laboris  nisi ut aliquip ex ea commodo consequat. Duis aute irure dolor in reprehend erit in voluptate velit esse cillum dolore eu fugiat la pariatur. Excepteur sint occaecat cupidatat non proident, sunt in culpa qui officia deserunt mollit anim id est laborum  <span> [task1] </span> super <ul><li> li 1 </li> <li> li 1 </li></ul> long html content witn images and html tags,  sed do eiusmod tempor incididunt ut labore et dolore magna aliqua. Ut enim ad minim veniam, quis nostrud exercitation ullamco laboris  nisi ut aliquip ex ea commodo consequat. Duis aute irure dolor in reprehend erit in voluptate velit esse cillum dolore eu fugiat la pariatur. Excepteur sint occaecat cupidatat non proident, sunt in culpa qui officia deserunt mollit anim id est laborum ",
                        "dateEnd": "27/12/2014"
                }
                ]
        }
        ]
        }

}
